{"id":1,"start":{"id":627,"title":"Trainspotting","year":1996},"goal":{"id":9023,"title":"Spirit: Stallion of the Cimarron","year":2002},"par":2,"films":{"2048":["I, Robot",2004],"1541":["Thelma & Louise",1991],"10501":["The Road to El Dorado",2000],"286217":["The Martian",2015],"140300":["Kung Fu Panda 3",2016],"9740":["Hannibal",2001],"361743":["Top Gun: Maverick",2022],"272":["Batman Begins",2005],"1562":["28 Weeks Later",2007],"285":["Pirates of the Caribbean: At World's End",2007],"9502":["Kung Fu Panda",2008],"10527":["Madagascar: Escape 2 Africa",2008],"10528":["Sherlock Holmes",2009],"297762":["Wonder Woman",2017],"35":["The Simpsons Movie",2007],"49444":["Kung Fu Panda 2",2011],"198184":["Chappie",2015],"809":["Shrek 2",2004],"298":["Ocean's Thirteen",2007],"359724":["Ford v Ferrari",2019],"1581":["The Holiday",2006],"565":["The Ring",2002],"351286":["Jurassic World: Fallen Kingdom",2018],"824":["Moulin Rouge!",2001],"58":["Pirates of the Caribbean: Dead Man's Chest",2006],"9023":["Spirit: Stallion of the Cimarron",2002],"6977":["No Country for Old Men",2007],"228161":["Home",2015],"27205":["Inception",2010],"911430":["F1",2025],"71":["Billy Elliot",2000],"9800":["Philadelphia",1993],"2118":["L.A. Confidential",1997],"9802":["The Rock",1996],"587":["Big Fish",2003],"321612":["Beauty and the Beast",2017],"9291":["The Longest Yard",2005],"1865":["Pirates of the Caribbean: On Stranger Tides",2011],"591":["The Da Vinci Code",2006],"110415":["Snowpiercer",2013],"2898":["As Good as It Gets",1997],"44115":["127 Hours",2010],"670292":["The Creator",2023],"855":["Black Hawk Down",2001],"857":["Saving Private Ryan",1998],"1369":["Rambo: First Blood Part II",1985],"7518":["Over the Hedge",2006],"44896":["Rango",2011],"98":["Gladiator",2000],"1635":["The Island",2005],"387426":["Okja",2017],"381284":["Hidden Figures",2016],"1893":["Star Wars: Episode I - The Phantom Menace",1999],"1894":["Star Wars: Episode II - Attack of the Clones",2002],"616":["The Last Samurai",2003],"1895":["Star Wars: Episode III - Revenge of the Sith",2005],"438631":["Dune",2021],"9837":["The Prince of Egypt",1998],"335984":["Blade Runner 2049",2017],"49521":["Man of Steel",2013],"39538":["Contagion",2011],"627":["Trainspotting",1996],"116":["Match Point",2005],"12405":["Slumdog Millionaire",2008],"68724":["Elysium",2013],"634":["Bridget Jones's Diary",2001],"380":["Rain Man",1988],"57212":["War Horse",2011],"49026":["The Dark Knight Rises",2012],"13448":["Angels & Demons",2009],"872585":["Oppenheimer",2023],"8587":["The Lion King",1994],"693134":["Dune: Part Two",2024],"1422":["The Departed",2006],"495764":["Birds of Prey (and the Fantabulous Emancipation of One Harley Quinn)",2020],"80278":["The Impossible",2012],"157336":["Interstellar",2014],"155":["The Dark Knight",2008],"411":["The Chronicles of Narnia: The Lion, the Witch and the Wardrobe",2005],"672":["Harry Potter and the Chamber of Secrets",2002],"321697":["Steve Jobs",2015],"161":["Ocean's Eleven",2001],"163":["Ocean's Twelve",2004],"676":["Pearl Harbor",2001],"38050":["The Adjustment Bureau",2011],"177572":["Big Hero 6",2014],"38055":["Megamind",2010],"170":["28 Days Later",2002],"76203":["12 Years a Slave",2013],"501170":["Doctor Sleep",2019],"617653":["The Last Duel",2021],"953":["Madagascar",2005],"1213":["The Talented Mr. Ripley",1999],"374720":["Dunkirk",2017],"80321":["Madagascar 3: Europe's Most Wanted",2012],"197":["Braveheart",1995],"2501":["The Bourne Identity",2002],"2502":["The Bourne Supremacy",2004],"2503":["The Bourne Ultimatum",2007],"58574":["Sherlock Holmes: A Game of Shadows",2011],"10191":["How to Train Your Dragon",2010],"96721":["Rush",2013],"420818":["The Lion King",2019],"9693":["Children of Men",2006],"62177":["Brave",2012],"44264":["True Grit",2010],"489":["Good Will Hunting",1997],"102382":["The Amazing Spider-Man 2",2014],"497":["The Green Mile",1999],"1272":["Sunshine",2007],"370172":["No Time to Die",2021]},"people":{"1":"George Lucas","2050":"Noah Huntley","3":"Harrison Ford","6":"Anthony Daniels","122889":"Dane DeHaan","2058":"Megan Burns","6159":"Ron Howard","215055":"Steven Yeun","6161":"Jennifer Connelly","6162":"Paul Bettany","19":"Allison Janney","6164":"Josh Lucas","6163":"Adam Goldberg","8210":"Wes Bentley","2071":"Mark Tildesley","2039":"Brendan Gleeson","1241113":"Mike Elliot","1304602":"An Seo-hyun","2070":"Chris Gill","31":"Tom Hanks","32":"Robin Wright","35":"Sally Field","18471":"Anthony Anderson","18472":"Kevin Corrigan","18473":"James Badge Dale","24618":"Paloma Baeza","6189":"Daniel P. Hanley","6190":"Mike Hill","137262":"Steve Purcell","48":"Sean Bean","1388593":"Jodie Comer","6193":"Leonardo DiCaprio","6195":"Harold Perrineau","112692":"Robert Maillet","52":"David Morse","24627":"Oliver Cotton","14386":"Beyoncé","10297":"Matthew McConaughey","62":"Bruce Willis","64":"Gary Oldman","14405":"Courteney Cox","14409":"David Schwimmer","4173":"Anthony Hopkins","85":"Johnny Depp","1304662":"Samuel Joslin","2144":"Tobin Bell","8289":"Billy Crudup","8291":"Alison Lohman","16483":"Sylvester Stallone","8293":"Marion Cotillard","8294":"Robert Guillaume","1552486":"Duncan Marjoribanks","8295":"Matthew McGrory","112742":"Emily Alyn Lind","28778":"Shirley Knight","28779":"Lupe Ontiveros","57452":"Faran Tahir","2157":"Robin Williams","1648751":"Ripley Sobo","112":"Cate Blanchett","113":"Christopher Lee","114":"Orlando Bloom","116":"Keira Knightley","118":"Geoffrey Rush","120":"Dariusz Wolski","2169":"Michael Jeter","2176":"Tommy Lee Jones","41091":"Kristen Wiig","131":"Jake Gyllenhaal","134":"Jamie Foxx","1124488":"Lisa Thoreson","140":"Lucy Liu","999565":"Joe Walker","147":"Michael Madsen","151":"Roger Deakins","4248":"Dennis Gassner","153":"Thomas Newman","8349":"Martin Sheen","2211":"Gerald R. Molen","16554":"Richard Crenna","82093":"Daniel Henney","28847":"Rafe Spall","2227":"Nicole Kidman","65717":"Jon Hamm","2231":"Samuel L. Jackson","104632":"Sylvia Hoeks","1026231":"Ploy Jindachote","67773":"Steve Martin","192":"Morgan Freeman","194":"Richard Harris","16578":"Julia Nickson","16580":"George Cheung","43202":"Antje Traue","198":"Dan Castellaneta","199":"Julie Kavner","200":"Nancy Cartwright","204":"Kate Winslet","205":"Kirsten Dunst","207":"Tom Wilkinson","213202":"Daniel Henshall","2258":"Stuart McQuarrie","212":"David Cross","1013973":"Carla Juri","8408":"Salvatore Totino","61659":"Chris Messina","966875":"Franklin Amobi","16607":"Alon Aboutboul","6368":"Embeth Davidtz","1290466":"Barry Keoghan","228":"Ed Harris","227564":"Benny Safdie","6383":"Aaron Eckhart","73968":"Henry Cavill","1837297":"Damson Idris","1241330":"Bashir Salahuddin","2296":"Clive Owen","12536":"Jack Thompson","2299":"Josh Hartnett","57597":"Ron Dean","8447":"Jeff Daniels","14592":"BD Wong","84225":"Gil Birmingham","20738":"Song Kang-ho","6413":"Danny Huston","149775":"Adam Paul","82191":"Sharlto Copley","35095":"John Rubano","1005852":"Janelle Monáe","139549":"Rory Kinnear","287":"Brad Pitt","41249":"Tess Harper","293":"Roger Pratt","84292":"John Oliver","326":"Kim Basinger","20806":"Silas Carson","10575":"Jess Gonchor","4431":"Jessica Lange","335":"Michael Shannon","2387":"Patrick Stewart","4443":"Christopher McDonald","1257819":"Daniella Pineda","349":"Scott Glenn","352":"Dennis Haysbert","43364":"Dakin Matthews","2405":"Audrey Tautou","12645":"Jeffrey DeMunn","12647":"Armin Mueller-Stahl","378":"Jonathan Pryce","4483":"Dustin Hoffman","388":"Jim Broadbent","1110405":"Mackenzie Davis","2440":"Bill Nighy","2441":"Tom Hollander","4492":"Philip Baker Hall","20879":"Kate Burton","400":"Geraldine Chaplin","2449":"Kevin McNally","4495":"Steve Carell","53651":"Monique Gabriela Curnen","53650":"Anthony Mackie","2453":"Mary Steenburgen","27030":"Tom Gallop","1360281":"Lashana Lynch","8602":"Alice Braga","59803":"Brenda Chapman","57755":"Woody Harrelson","33181":"Jimmy Smits","2462":"Catherine McCormack","33182":"Jay Laga'aia","2464":"Angus Macfadyen","225692":"Jeremy Irvine","2461":"Mel Gibson","2467":"James Cosmo","4515":"Treat Williams","2463":"Patrick McGoohan","33190":"Pernilla August","2465":"James Robinson","20904":"James Hong","4520":"William Forsythe","2468":"Sean McGinley","2469":"Gerda Stevenson","33196":"Jake Lloyd","18863":"Eric Darnell","18864":"Tom McGrath","2483":"John Toll","2484":"Steven Rosenblum","2486":"Thomas E. Sanders","72118":"Anil Kapoor","6585":"Perla Haney-Jardine","16828":"Chris Evans","31164":"Adewale Akinnuoye-Agbaje","131519":"Rihanna","449":"Jay Baruchel","454":"Michael Peña","2505":"James Cromwell","8654":"Matthew Modine","18897":"Jackie Chan","53714":"Rachel McAdams","16851":"Josh Brolin","1221073":"Will Merrick","6613":"Minnie Driver","4566":"Alan Rickman","6614":"Cole Hauser","6615":"John Mighton","473":"Brian Tufano","102873":"Patrice Vermette","6616":"Rachel Majorowski","2524":"Tom Hardy","477":"Julie Walters","478":"Jamie Bell","479":"Jamie Draven","480":"Gary Lewis","481":"Jean Heywood","16866":"Jennifer Lopez","482":"Stuart Wells","27102":"Wanda Sykes","16861":"John Hawkes","1296867":"Ankur Vikal","1419742":"Makenzie Moss","488":"Steven Spielberg","491":"John Williams","492":"Janusz Kamiński","493":"Michael Kahn","8687":"Chi McBride","25072":"Oscar Isaac","8688":"Diego Luna","500":"Tom Cruise","78324":"Jamie Chung","12790":"Charlie Hofheimer","12791":"Hugh Dancy","20982":"Marton Csokas","514":"Jack Nicholson","518":"Danny DeVito","519":"Martin Short","90633":"Gal Gadot","6668":"Christian Wagner","524":"Natalie Portman","21007":"Jonah Hill","529":"Guy Pearce","531":"Danny Elfman","51732":"Rodger Boyce","51733":"Ana Reeder","534":"Mark Boone Junior","1477143":"Joseph Balderrama","537":"Stephen Tobolowsky","10779":"David Calder","541":"Chris Lebenzon","61981":"Michael Clarke Duncan","80416":"Richard McGonagle","2593":"Rupert Gregson-Williams","12833":"Edward Burns","12834":"Barry Pepper","12835":"Vin Diesel","12836":"Ted Danson","16935":"Geena Davis","14887":"Paddy Considine","6623":"Vik Sahay","1057324":"Meredith Wells","16940":"Jeremy Irons","4654":"Jeremy Davies","559":"Wally Pfister","12852":"Barry Corbin","29237":"Leo Bill","18997":"Bryce Dallas Howard","18999":"J.K. Simmons","41527":"Remo Girone","578":"Ridley Scott","2632":"Chris Rock","585":"Rutger Hauer","6730":"Sacha Baron Cohen","587":"Edward James Olmos","8783":"Eric Bana","8784":"Daniel Craig","8786":"Ayelet Zurer","4690":"Christopher Walken","16984":"Bernat Vilaplana","21088":"Alan Tudyk","21089":"Bruce Greenwood","21090":"Adrian Ricard","21091":"Jerry Wasserman","6752":"Željko Ivanek","39520":"Garret Dillahunt","62064":"Chris Pine","86654":"Austin Butler","45702":"Paul Martin Smith","21134":"John Slattery","6800":"David Tattersall","658":"Alfred Molina","659":"Wolf Kahler","4756":"Matthew Broderick","6804":"Graham Greene","6806":"Doug Hutchison","101015":"Chin Han","2712":"Michael Biehn","62105":"Kerry Condon","6807":"Sam Rockwell","17051":"James Franco","17052":"Topher Grace","4765":"Jason Robards","670":"Ben Burtt","15009":"Justin Theroux","51878":"John Kani","679":"Franka Potente","17064":"Ben Whishaw","10920":"Tobias Menzies","4785":"Jeff Goldblum","467633":"Adepero Oduye","1364660":"April Lawrence","51894":"J. A. Bayona","27319":"Christoph Waltz","121529":"Léa Seydoux","51898":"Óscar Faura","4808":"Giancarlo Esposito","4810":"Rosie Perez","68307":"Luke Mably","10965":"Chris Columbus","13014":"Toby Jones","60118":"John Bedford Lloyd","6875":"Peter Honess","13022":"Tom Berenger","29406":"Joey Ansah","76512":"Jason Clarke","936672":"Jessica Schulte","738":"Sean Connery","8930":"John Cleese","191202":"Matt Jones","10980":"Daniel Radcliffe","10983":"Richard Griffiths","39659":"Burn Gorman","10989":"Rupert Grint","10990":"Emma Watson","8945":"Kevin Kline","10993":"Tom Felton","17140":"Abigail Breslin","17141":"Greg Kinnear","17142":"Paul Dano","74487":"David Pasquesi","74488":"Cosimo Fusco","37625":"Andrew Garfield","765":"Hiam Abbass","74494":"Victor Alfieri","469759":"Àstrid Bergès-Frisbey","166654":"Ethan Sandler","6913":"Ellen Barkin","76547":"Aksel Hennie","29445":"Ethan Phillips","776":"Eddie Murphy","11017":"Elliot Graham","11018":"Guy Hendrix Dyas","1190668":"Timothée Chalamet","782":"Steven Berkoff","51988":"Lizzy Caplan","51990":"T.J. Miller","8986":"James Rebhorn","6941":"Cameron Diaz","6944":"Octavia Spencer","56100":"Alistair Petrie","119589":"Donald Glover","56103":"Hattie Morahan","9001":"Masahiro Hirakubo","543530":"Dave Bautista","9003":"Kave Quinn","17199":"Corey Johnson","15152":"James Earl Jones","23346":"Armand Assante","49971":"Jennifer Ehle","9012":"Jonny Lee Miller","9013":"Kevin McKidd","4068148":"Madeleine Yuna Voyles","9015":"Kelly Macdonald","9016":"Eileen Nicholas","9017":"Pauline Lynch","6968":"Hugh Jackman","11064":"David Strathairn","6972":"Ian McShane","56117":"Martin Kove","827":"Elliott Gould","2882":"Diane Lane","21316":"Nestor Carbonell","4935":"Pete Postlethwaite","2888":"Will Smith","74568":"Chris Hemsworth","19274":"Seth Rogen","11098":"John Powell","19292":"Adam Sandler","17244":"Hayden Christensen","865":"Michael Bay","21345":"Stephen Mangan","142182":"Sean Bott","1823591":"Eugene Brave Rock","880":"Ben Affleck","84848":"Loudon Wainwright III","234352":"Margot Robbie","884":"Steve Buscemi","1237876":"David Ury","886":"William Fichtner","2175867":"Ella Jay Basco","892":"John Schwartzman","17276":"Gerard Butler","84865":"William Houston","898":"Mark Goldblatt","17288":"Michael Fassbender","78729":"Nathan Lane","117642":"Jason Momoa","2955":"Chris Cooper","11148":"Joan Allen","2954":"Jeffrey Wright","7056":"Emma Thompson","2963":"Nicolas Cage","920":"Jürgen Prochnow","9138":"Gemma Jones","2975":"Laurence Fishburne","934":"Russell Crowe","935":"Connie Nielsen","2983":"Mark Strong","936":"Oliver Reed","938":"Djimon Hounsou","13227":"Jay Cassidy","940":"John Shrapnel","11181":"Kenneth Branagh","937":"Derek Jacobi","939":"David Schofield","944":"Arthur Max","17328":"Rufus Sewell","941":"Tomas Arana","947":"Hans Zimmer","948":"Lisa Gerrard","942":"Ralf Moeller","950":"Pietro Scalia","9137":"Renée Zellweger","5048":"Harry Dean Stanton","5049":"John Hurt","27578":"Elliot Page","955":"Penélope Cruz","956":"Guy Ritchie","15293":"Keisha Castle-Hughes","72638":"Tracy Letts","9145":"James Callis","9144":"Sally Phillips","13240":"Mark Wahlberg","13242":"Paul Giamatti","9152":"Patrick Doyle","195525":"Miranda Raison","11207":"David Thewlis","1780681":"Kendal Cronkhite","1379277":"Alex Lawther","11213":"Pam Ferris","11218":"Alfonso Cuarón","146391":"Brian Stepanek","5081":"Emily Blunt","15327":"Nathan Crowley","2118623":"Kyliegh Curran","31711":"Troy Garity","9188":"Billy Connolly","9189":"Shichinosuke Nakamura","9190":"Koyuki","9191":"Timothy Spall","142312":"Jennifer Yuh Nelson","9192":"Togo Igawa","9194":"Shin Koyamada","9195":"Hiroyuki Sanada","1003":"Jean Reno","1389549":"Céline Buckens","27631":"Nathaniel Parker","15347":"Michael Giacchino","76788":"Dev Patel","3061":"Ewan McGregor","15349":"Maryann Brandon","3063":"Tilda Swinton","76792":"Freida Pinto","3064":"Peter Mullan","17401":"Stephen Root","1018":"Nikolaj Lie Kaas","76789":"Saurabh Shukla","76793":"Irrfan Khan","56323":"Tina Fey","1526793":"Sturgill Simpson","17419":"Bryan Cranston","11275":"Stephen Fry","1037":"Harvey Keitel","1038":"Jodie Foster","25616":"Edgar Ramírez","66580":"Scott Adsit","1616920":"Amar Chadha-Patel","5145":"Jack Murdock","93210":"Domhnall Gleeson","25626":"Robert Ridgely","11291":"Clémence Poésy","5146":"Michael D. Roberts","5147":"Ralph Seymour","5151":"Beth Grant","5148":"Lucinda Jenney","59233":"Scoot McNairy","130081":"Robin Atkin Downes","5149":"Bonnie Hunt","50217":"Michael Kelly","19498":"Jon Bernthal","56365":"Charlie Hunnam","44079":"Charlotte Rampling","3124":"Valeria Golino","93236":"David Dencik","7222":"Chopper Bernet","9273":"Amy Adams","83002":"Jessica Chastain","3131":"Antonio Banderas","154684":"Siobhan Flynn","7229":"Marco Beltrami","9278":"Jennifer Garner","17477":"Harriet Walter","1508424":"Kathy Altieri","7242":"Temuera Morrison","17486":"Alison Pill","7248":"Cliff Curtis","15440":"Jared Harris","195666":"Sharon Duncan-Brewster","44119":"Nick Fletcher","17498":"Niels Arestrup","11355":"Jason Isaacs","1115":"Stephen Graham","27740":"Walton Goggins","62562":"David Denman","40036":"Taraji P. Henson","1125":"Ewen Bremner","932967":"Mahershala Ali","1129":"Sławomir Idziak","11370":"Elton John","23659":"Will Ferrell","17521":"Kelly Reilly","27762":"Ian McDiarmid","1141877":"Ariana Neal","154742":"Troy Blendell","3197":"Tom Sizemore","1117313":"John David Washington","1158":"Al Pacino","58502":"Natalie Dormer","1160":"Michelle Pfeiffer","54415":"Josh Gad","3223":"Robert Downey Jr.","72855":"Felicity Jones","21657":"Vera Farmiga","1039523":"Dylan Arnold","1023139":"Adam Driver","72873":"Michael Stuhlbarg","5292":"Denzel Washington","5294":"Chiwetel Ejiofor","31923":"Oliver Ford Davies","1204":"Julia Roberts","31925":"Hugh Quarshie","21689":"Ko A-sung","3265":"Eli Wallach","70851":"Jack Black","17604":"Jeremy Renner","52419":"Josh Hamilton","17606":"Imogen Poots","1223":"Joel Coen","1224":"Ethan Coen","1225":"Carter Burwell","17607":"Mackintosh Muggleton","1226":"Rick Heinrichs","1229":"Jeff Bridges","1231":"Julianne Moore","124112":"Charles Parnell","27855":"Shannyn Sossamon","1233":"Philip Seymour Hoffman","11477":"Ray Liotta","87257":"Cary Joji Fukunaga","3291":"Hugh Grant","1244":"Jonathan Rhys Meyers","1245":"Scarlett Johansson","1246":"Emily Mortimer","1247":"Matthew Goode","1248":"Brian Cox","1249":"Penelope Wilton","17628":"Mary Elizabeth Winstead","34019":"Marta Etura","58587":"Phaldut Sharma","1253":"Jim Clay","7399":"Ben Stiller","81134":"Oana Pellea","2002163":"Sylvie Macdonald","1269":"Kevin Costner","9462":"Randall Duk Kim","1271":"Andy Garcia","9464":"Harry Lennix","1414389":"Archie Macdonald","5374":"Jim Parsons","224513":"Ana de Armas","1283":"Helena Bonham Carter","1294":"Missi Pyle","1301":"Philippe Rousselot","83222":"Shane McRae","7447":"Alec Baldwin","17691":"Miffy Englefield","17692":"Emma Pritchard","17693":"Sarah Parish","17695":"Bill Macy","220448":"Paul Anderson","97576":"Gemma Chan","19755":"Kevin Thompson","5419":"Saïd Taghmaoui","60716":"Bob Sapp","1327":"Ian McKellen","3398":"Kim Bodnia","83271":"Glen Powell","7499":"Jared Leto","56658":"Daniel Studi","56659":"Jeff LeBeau","56660":"Lorna Cook","154968":"Noa Tishby","3417":"Tony Goldwyn","9560":"Ellen Burstyn","1372":"Karl Urban","5469":"Ralph Fiennes","996701":"Miles Teller","5472":"Colin Firth","114019":"Luke Evans","56678":"Clare Knight","9575":"Jada Pinkett Smith","52583":"Wagner Moura","5488":"Gabriel Yared","5491":"Stuart Craig","933238":"Rebecca Ferguson","138619":"Philip McGrade","9599":"Cloris Leachman","30082":"Benedict Wong","42376":"Zahn McClarnon","62862":"Danny McBride","5524":"Andrew Adamson","1430":"Keith Richards","175511":"Matt Levin","5528":"William Moseley","5529":"Anna Popplewell","5530":"James McAvoy","5527":"Skandar Keynes","13724":"Jane Alexander","5526":"Georgie Henley","13726":"Ned Beatty","5532":"Judy McIntosh","3489":"Naomi Watts","5538":"Ray Winstone","5539":"Dawn French","54691":"Christopher Mintz-Plasse","54693":"Emma Stone","5542":"Sim Evan-Jones","9642":"Jude Law","17838":"Rami Malek","17839":"Pierfrancesco Favino","5553":"Harry Gregson-Williams","11701":"Angelina Jolie","1461":"George Clooney","515510":"Ryan Potter","11705":"Michelle Monaghan","1472":"Ray McKinnon","1052100":"Sally Kinghorn","15814":"Mark A. Hester","5576":"Val Kilmer","1052109":"Harry Styles","85456":"Mahesh Manjrekar","95697":"Dileep Rao","5586":"Yeardley Smith","5587":"Hank Azaria","34259":"Jean-Yves Berteloot","116180":"Byun Hee-bong","91606":"Tom Hiddleston","15831":"Frank Welker","64986":"Clare-Hope Ashitey","60898":"Sebastian Stan","1590759":"Noah Jupe","24045":"Joseph Gordon-Levitt","15854":"Ted Levine","214516":"Robert Cait","11764":"Ian Abercrombie","58873":"Dan Fogler","1687041":"Fionn Whitehead","1113604":"Peigi Barker","69127":"Michael Irvin","69128":"Nelly","5644":"Alexandra Maria Lara","77335":"Ben Mendelsohn","1570":"Anthony Dod Mantle","20005":"Moira Kelly","39390":"Michael Kenneth Williams","1373737":"Florence Pugh","134698":"Haydn Gwynne","67113":"Greig Fraser","1580":"Daveigh Chase","1579":"Maggie Gyllenhaal","15915":"Sergio Rubini","15916":"Fiorello","3627":"Paz Vega","9777":"Cuba Gooding Jr.","7732":"Allan Cameron","79416":"Robert Longstreet","54856":"Jarlath Conroy","1207881":"Oaklee Pendergast","11855":"Geraldine James","130640":"Hailee Steinfeld","26192":"Alwin H. Küchler","196179":"Stephen McKinley Henderson","1620":"Michelle Yeoh","56917":"James Herbert","1622":"Chang Chen","9817":"Nigel Phelps","5723":"John Leguizamo","5726":"Cedric the Entertainer","9827":"Rose Byrne","18023":"Robert Carlyle","1640":"Stellan Skarsgård","11880":"Claire Simpson","1639":"Emily Watson","13936":"Frankie Faison","147056":"Caitríona Balfe","169586":"Vanessa Marcil","52848":"Isla Fisher","1665":"Eddie Marsan","52865":"Garry Shandling","1267329":"Lupita Nyong'o","18053":"Jamie McBride","59017":"Jurnee Smollett","579211":"Damien Bonnard","9880":"Sam Shepard","18082":"Timothy Olyphant","1704":"Gore Verbinski","3753":"Giancarlo Giannini","87722":"Noomi Rapace","1709":"Jack Davenport","1710":"Lee Arenberg","1711":"Mackenzie Crook","126638":"Mark Andrews","26291":"Martin Henderson","26292":"David Dorfman","26293":"Rachael Bella","26294":"Lindsay Frost","1715":"David Bailie","1721":"Stephen E. Rivkin","34490":"Sarah Paulson","5823":"Julie Andrews","1729":"James Horner","1733":"Nick Nolte","24264":"Craig Ferguson","32458":"Gabriel Mann","73421":"Joaquin Phoenix","1748":"William Shatner","20191":"Jose Pablo Cantillo","3810":"Javier Bardem","7907":"John Ratzenberger","7908":"Frank Oz","141034":"Billy Magnussen","1771":"Giovanni Ribisi","73457":"Chris Pratt","16119":"Charles Napier","145143":"Aneurin Barnard","126713":"Elizabeth Marvel","12041":"Julia Stiles","9994":"Helen Hunt","87822":"Damon Wayans Jr.","1810":"Heath Ledger","12052":"Gwyneth Paltrow","1813":"Anne Hathaway","1136406":"Tom Holland","1156888":"Tom Cross","5915":"Jaime King","3872":"Daniel Brühl","20258":"Thure Lindhardt","59174":"America Ferrera","69415":"Ernie Sabella","12073":"Mike Myers","1834":"Shirley Henderson","12074":"John Lithgow","1837":"Susan Vidler","12077":"Jim Cummings","12079":"Kelly Asbury","36656":"Sarah Greenwood","1029934":"Justice Smith","12080":"Conrad Vernon","3894":"Christian Bale","3895":"Michael Caine","3896":"Liam Neeson","3897":"Katie Holmes","3899":"Ken Watanabe","3900":"Linus Roache","20286":"Toby Kebbell","12097":"Christopher Knights","12098":"Chris Miller","3910":"Frances McDormand","851784":"Mackenzie Foy","61260":"Paul Rae","32592":"Ron Vawter","3926":"Albert Finney","1828695":"JD McCrary","18265":"Mauro Fiore","221018":"Dan Stevens","1884":"Steven Soderbergh","1889":"David Holmes","1681250":"Raymond Zibach","1891":"Stephen Mirrione","1892":"Matt Damon","18277":"Sandra Bullock","1893":"Casey Affleck","1894":"Scott Caan","1896":"Don Cheadle","1897":"Bernie Mac","1898":"Eddie Jemison","1890":"Philip Messina","1900":"Shaobo Qin","505710":"Zendaya","6008":"Harry Shearer","3967":"Kate Beckinsale","51072":"Kate Mara","20354":"Amber Tamblyn","34691":"John Spencer","1923":"Robbie Coltrane","1925":"Vincent Cassel","1922":"Catherine Zeta-Jones","10123":"Roger Barton","10127":"Jon Voight","10128":"William Lee Scott","10129":"Greg Zola","10130":"Catherine Kellner","237455":"Sam Claflin","10132":"Colm Feore","30614":"Ryan Gosling","10135":"Jesse James","235416":"Sarah Snook","34715":"James Nesbitt","71580":"Benedict Cumberbatch","1957":"Sophie Marceau","65447":"Sarah Niles","12206":"Richard Roxburgh","112561":"Lily Collins","18354":"Bridget Moynahan","12211":"Garry McDonald","12210":"Jacek Koman","12212":"Matthew Whittet","59315":"Olivia Wilde","1979":"Kevin Spacey","1981":"Alfre Woodard","4031":"Greg Ellis","40900":"Mark Rylance","964549":"Madhur Mittal","4038":"Susan Sarandon","1989":"Celia Weston","985040":"Yo-Landi Visser","985041":"Ninja","1853396":"Selena Anduze","198615":"Chris Shields","591835":"Ali Wong","10205":"Sigourney Weaver","28637":"Andy Richter","28641":"Terence Stamp","77795":"Katherine Waterston","20463":"Mark Digby","1318896":"Lisa Summerour","2034":"Danny Boyle","2037":"Cillian Murphy","2038":"Naomie Harris","147446":"Sönke Möhring","2040":"Christopher Eccleston","63484":"Fenton Quinn","2047":"Danny Glover"},"edges":[[2048,2888],[2048,18354],[2048,21088],[2048,2505],[2048,21089],[2048,21090],[2048,8687],[2048,21091],[2048,7229],[1541,4038],[1541,16935],[1541,1037],[1541,147],[1541,4443],[1541,537],[1541,287],[1541,5148],[1541,578],[1541,947],[10501,11181],[10501,8945],[10501,4810],[10501,23346],[10501,587],[10501,12077],[10501,15831],[10501,2144],[10501,11370],[10501,1552486],[10501,947],[10501,11098],[286217,1892],[286217,83002],[286217,41091],[286217,8447],[286217,454],[286217,48],[286217,51072],[286217,60898],[286217,76547],[286217,5294],[286217,30082],[286217,1110405],[286217,578],[286217,950],[286217,944],[286217,120],[286217,5553],[140300,70851],[140300,17419],[140300,4483],[140300,11701],[140300,18999],[140300,18897],[140300,19274],[140300,140],[140300,212],[140300,20904],[140300,9462],[140300,142312],[140300,947],[140300,56678],[140300,1681250],[9740,4173],[9740,1231],[9740,64],[9740,11477],[9740,3753],[9740,6752],[9740,13936],[9740,578],[9740,950],[9740,947],[361743,500],[361743,996701],[361743,6161],[361743,1241330],[361743,65717],[361743,124112],[361743,83271],[361743,5576],[361743,947],[272,3894],[272,3895],[272,3896],[272,3897],[272,64],[272,2037],[272,207],[272,585],[272,3899],[272,534],[272,3900],[272,192],[272,947],[272,559],[272,15327],[1562,18023],[1562,9827],[1562,17604],[1562,6195],[1562,2462],[1562,17607],[1562,17606],[1562,2071],[1562,2070],[285,85],[285,118],[285,114],[285,116],[285,1709],[285,2440],[285,378],[285,1710],[285,1711],[285,2449],[285,1715],[285,1640],[285,1704],[285,947],[285,120],[285,1721],[285,1226],[9502,70851],[9502,4483],[9502,11701],[9502,6972],[9502,19274],[9502,140],[9502,212],[9502,9462],[9502,20904],[9502,58873],[9502,61981],[9502,18897],[9502,947],[9502,11098],[9502,1681250],[10527,7399],[10527,2632],[10527,14409],[10527,9575],[10527,6730],[10527,5726],[10527,28637],[10527,1897],[10527,7447],[10527,18864],[10527,18863],[10527,1780681],[10527,947],[10527,15814],[10528,3223],[10528,9642],[10528,53714],[10528,2983],[10528,1665],[10528,112692],[10528,11855],[10528,17521],[10528,84865],[10528,36656],[10528,956],[10528,56917],[10528,1301],[10528,947],[297762,90633],[297762,62064],[297762,935],[297762,32],[297762,6413],[297762,11207],[297762,5419],[297762,1125],[297762,1823591],[297762,2593],[35,198],[35,199],[35,200],[35,5586],[35,5587],[35,6008],[35,947],[49444,70851],[49444,11701],[49444,4483],[49444,64],[49444,18897],[49444,140],[49444,19274],[49444,212],[49444,1620],[49444,20904],[49444,62862],[49444,352],[49444,142312],[49444,947],[49444,11098],[49444,15349],[49444,56678],[49444,1681250],[198184,82191],[198184,76788],[198184,6968],[198184,985041],[198184,985040],[198184,10205],[198184,198615],[198184,20191],[198184,947],[198184,898],[809,12073],[809,776],[809,6941],[809,5823],[809,3131],[809,8930],[809,12079],[809,12080],[809,12080],[809,5542],[809,12079],[809,5524],[809,5553],[298,1461],[298,287],[298,1158],[298,1892],[298,1896],[298,1897],[298,6913],[298,1893],[298,1894],[298,1271],[298,1884],[298,1889],[298,1891],[298,1884],[298,1890],[359724,1892],[359724,3894],[359724,19498],[359724,147056],[359724,6164],[359724,1590759],[359724,72638],[359724,41527],[359724,1472],[359724,7229],[1581,6941],[1581,204],[1581,9642],[1581,70851],[1581,3265],[1581,12833],[1581,17328],[1581,17691],[1581,17692],[1581,17693],[1581,27855],[1581,17695],[1581,947],[565,3489],[565,26291],[565,26292],[565,1248],[565,13724],[565,26294],[565,20354],[565,26293],[565,1580],[565,947],[565,1704],[351286,73457],[351286,18997],[351286,28847],[351286,1029934],[351286,1257819],[351286,2505],[351286,13014],[351286,15854],[351286,4785],[351286,14592],[351286,400],[351286,51894],[351286,15347],[351286,16984],[351286,51898],[824,3061],[824,2227],[824,5723],[824,388],[824,12206],[824,12211],[824,12210],[824,12212],[58,85],[58,114],[58,116],[58,1709],[58,2440],[58,378],[58,1710],[58,1711],[58,2449],[58,1715],[58,1640],[58,2441],[58,1704],[58,120],[58,1226],[58,947],[58,1721],[9023,1892],[9023,2505],[9023,56658],[9023,7222],[9023,56659],[9023,35095],[9023,80416],[9023,175511],[9023,149775],[9023,214516],[9023,16119],[9023,1057324],[9023,12079],[9023,56678],[9023,56660],[9023,947],[9023,1508424],[6977,3810],[6977,2176],[6977,16851],[6977,57755],[6977,9015],[6977,39520],[6977,41249],[6977,12852],[6977,17401],[6977,51732],[6977,5151],[6977,51733],[6977,1223],[6977,151],[6977,10575],[6977,1224],[6977,1225],[6977,1223],[6977,1224],[228161,5374],[228161,131519],[228161,67773],[228161,16866],[228161,191202],[228161,146391],[228161,1364660],[228161,44119],[228161,1508424],[27205,6193],[27205,24045],[27205,3899],[27205,2524],[27205,27578],[27205,95697],[27205,2037],[27205,13022],[27205,8293],[27205,4935],[27205,3895],[27205,559],[27205,11018],[27205,947],[911430,287],[911430,1837297],[911430,3810],[911430,62105],[911430,10920],[911430,3398],[911430,65447],[911430,1221073],[911430,1477143],[911430,2071],[911430,947],[911430,1891],[71,478],[71,480],[71,477],[71,481],[71,479],[71,482],[71,1241113],[71,473],[9800,31],[9800,5292],[9800,4765],[9800,2453],[9800,3131],[9800,32592],[9800,25626],[9800,16119],[9800,1318896],[2118,1979],[2118,934],[2118,529],[2118,2505],[2118,326],[2118,518],[2118,11064],[2118,6875],[9802,738],[9802,2963],[9802,228],[9802,34691],[9802,52],[9802,4520],[9802,2712],[9802,169586],[9802,865],[9802,892],[9802,947],[587,3061],[587,3926],[587,8289],[587,4431],[587,1283],[587,8291],[587,8294],[587,8293],[587,8295],[587,62562],[587,1294],[587,84848],[587,531],[587,541],[587,1301],[587,4248],[321612,10990],[321612,221018],[321612,114019],[321612,8945],[321612,7056],[321612,3061],[321612,54415],[321612,56103],[321612,134698],[321612,1327],[321612,36656],[9291,19292],[9291,2632],[9291,2505],[9291,69128],[9291,69127],[9291,60716],[9291,886],[9291,9599],[9291,14405],[1865,85],[1865,955],[1865,118],[1865,6972],[1865,2449],[1865,237455],[1865,469759],[1865,1115],[1865,1430],[1865,10983],[1865,4031],[1865,947],[1865,120],[591,31],[591,2405],[591,1327],[591,1003],[591,6162],[591,658],[591,920],[591,34259],[591,6159],[591,947],[591,8408],[591,6189],[591,6190],[591,7732],[110415,16828],[110415,20738],[110415,228],[110415,5049],[110415,3063],[110415,478],[110415,6944],[110415,1125],[110415,21689],[110415,17486],[110415,7229],[2898,514],[2898,9994],[2898,17141],[2898,9777],[2898,28778],[2898,10135],[2898,5586],[2898,28779],[2898,947],[44115,17051],[44115,51072],[44115,20354],[44115,11291],[44115,51988],[44115,20879],[44115,4515],[44115,142182],[44115,63484],[44115,2034],[44115,1570],[670292,1117313],[670292,4068148],[670292,97576],[670292,19],[670292,3899],[670292,1526793],[670292,1616920],[670292,67113],[670292,999565],[670292,947],[855,2299],[855,8783],[855,3061],[855,3197],[855,886],[855,9880],[855,11355],[855,1125],[855,114],[855,2524],[855,12790],[855,12791],[855,1129],[855,944],[855,950],[855,578],[855,947],[857,31],[857,3197],[857,12833],[857,12834],[857,6163],[857,12835],[857,1771],[857,4654],[857,1892],[857,12836],[857,13242],[857,488],[857,493],[857,2486],[857,491],[857,492],[1369,16483],[1369,16554],[1369,16119],[1369,782],[1369,16578],[1369,56117],[1369,16580],[1369,898],[7518,62],[7518,52865],[7518,4495],[7518,27102],[7518,1748],[7518,1733],[7518,19],[7518,2593],[7518,1508424],[44896,85],[44896,52848],[44896,13726],[44896,2440],[44896,17140],[44896,658],[44896,17401],[44896,5048],[44896,18082],[44896,5538],[44896,11764],[44896,84225],[44896,1704],[44896,947],[44896,151],[98,934],[98,73421],[98,935],[98,936],[98,194],[98,937],[98,938],[98,939],[98,940],[98,941],[98,942],[98,578],[98,944],[98,947],[98,948],[98,950],[1635,3061],[1635,1245],[1635,938],[1635,48],[1635,884],[1635,61981],[1635,29445],[1635,146391],[1635,154968],[1635,154684],[1635,154742],[1635,18053],[1635,9817],[1635,6668],[1635,865],[1635,18265],[387426,1304602],[387426,3063],[387426,17142],[387426,215055],[387426,131],[387426,4808],[387426,116180],[387426,112561],[387426,213202],[387426,1834],[387426,19755],[381284,40036],[381284,6944],[381284,1005852],[381284,1269],[381284,205],[381284,5374],[381284,932967],[381284,83271],[381284,1141877],[381284,947],[1893,3896],[1893,3061],[1893,524],[1893,33196],[1893,27762],[1893,33190],[1893,31923],[1893,31925],[1893,6],[1893,7908],[1893,1],[1893,6800],[1893,491],[1893,670],[1893,45702],[1894,17244],[1894,3061],[1894,524],[1894,113],[1894,2231],[1894,7908],[1894,27762],[1894,33190],[1894,7242],[1894,33181],[1894,12536],[1894,6800],[1894,1],[1894,491],[1894,670],[616,500],[616,3899],[616,9191],[616,3417],[616,9195],[616,9190],[616,9194],[616,9188],[616,9192],[616,9189],[616,2483],[616,947],[616,2484],[1895,17244],[1895,3061],[1895,524],[1895,27762],[1895,2231],[1895,33181],[1895,7908],[1895,6],[1895,113],[1895,15293],[1895,20806],[1895,33182],[1895,670],[1895,1],[1895,491],[1895,10123],[1895,6800],[438631,1190668],[438631,933238],[438631,25072],[438631,117642],[438631,1640],[438631,196179],[438631,16851],[438631,3810],[438631,195666],[438631,1622],[438631,543530],[438631,67113],[438631,999565],[438631,947],[438631,102873],[9837,5576],[9837,5469],[9837,1160],[9837,18277],[9837,4785],[9837,2047],[9837,2387],[9837,67773],[9837,519],[9837,59803],[9837,44119],[9837,947],[335984,30614],[335984,3],[335984,224513],[335984,543530],[335984,32],[335984,104632],[335984,1110405],[335984,7499],[335984,1013973],[335984,765],[335984,151],[335984,999565],[335984,4248],[335984,947],[49521,73968],[49521,9273],[49521,335],[49521,2882],[49521,934],[49521,43202],[49521,9464],[49521,1269],[49521,8786],[49521,2975],[49521,947],[39538,8293],[39538,1892],[39538,2975],[39538,9642],[39538,204],[39538,49971],[39538,12052],[39538,17419],[39538,827],[39538,101015],[39538,16861],[39538,1884],[39538,1884],[39538,1891],[627,3061],[627,1125],[627,9012],[627,9013],[627,18023],[627,9015],[627,3064],[627,2467],[627,9016],[627,1837],[627,9017],[627,1834],[627,473],[627,2034],[627,9001],[627,9003],[116,1244],[116,1245],[116,1246],[116,1247],[116,1248],[116,1249],[116,34715],[116,1125],[116,195525],[116,20286],[116,1253],[12405,76788],[12405,76792],[12405,964549],[12405,72118],[12405,85456],[12405,76789],[12405,76793],[12405,1296867],[12405,2034],[12405,1570],[12405,20463],[68724,1892],[68724,1038],[68724,82191],[68724,8688],[68724,52583],[68724,8602],[68724,886],[68724,20191],[68724,57452],[634,9137],[634,5472],[634,3291],[634,388],[634,9138],[634,9145],[634,9144],[634,1834],[634,6368],[634,9152],[380,4483],[380,500],[380,3124],[380,2211],[380,5145],[380,5146],[380,5147],[380,5148],[380,5149],[380,5151],[380,947],[57212,225692],[57212,3064],[57212,1639],[57212,17498],[57212,11207],[57212,91606],[57212,71580],[57212,1389549],[57212,20286],[57212,488],[57212,493],[57212,492],[57212,491],[49026,3894],[49026,64],[49026,2524],[49026,24045],[49026,1813],[49026,8293],[49026,192],[49026,3895],[49026,8654],[49026,16607],[49026,77335],[49026,39659],[49026,947],[49026,15327],[49026,559],[13448,31],[13448,3061],[13448,8786],[13448,1640],[13448,17839],[13448,1018],[13448,12647],[13448,20258],[13448,74487],[13448,74488],[13448,74494],[13448,966875],[13448,6159],[13448,6190],[13448,947],[13448,8408],[13448,6189],[13448,7732],[872585,2037],[872585,5081],[872585,1892],[872585,3223],[872585,1373737],[872585,2299],[872585,1893],[872585,17838],[872585,11181],[872585,227564],[872585,76512],[872585,1039523],[8587,4756],[8587,20005],[8587,16940],[8587,78729],[8587,69415],[8587,15152],[8587,8294],[8587,12077],[8587,947],[693134,1190668],[693134,505710],[693134,933238],[693134,3810],[693134,16851],[693134,86654],[693134,1373737],[693134,543530],[693134,4690],[693134,121529],[693134,1640],[693134,44079],[693134,999565],[693134,947],[693134,102873],[693134,67113],[1422,6193],[1422,1892],[1422,514],[1422,13240],[1422,8349],[1422,5538],[1422,21657],[1422,18471],[1422,7447],[1422,18472],[1422,18473],[495764,234352],[495764,4810],[495764,17628],[495764,59017],[495764,3061],[495764,2175867],[495764,61659],[495764,591835],[495764,1237876],[495764,13227],[80278,3489],[80278,3061],[80278,1136406],[80278,1304662],[80278,1207881],[80278,34019],[80278,147446],[80278,400],[80278,1026231],[80278,51894],[80278,51898],[80278,16984],[157336,10297],[157336,1813],[157336,3895],[157336,83002],[157336,1893],[157336,8210],[157336,17052],[157336,851784],[157336,9560],[157336,12074],[157336,947],[157336,15327],[155,3894],[155,1810],[155,6383],[155,3895],[155,1579],[155,64],[155,192],[155,53651],[155,57597],[155,2037],[155,101015],[155,21316],[155,947],[155,559],[155,15327],[411,5528],[411,5529],[411,5527],[411,5526],[411,3896],[411,3063],[411,5530],[411,388],[411,5538],[411,5539],[411,2467],[411,5532],[411,5553],[411,5542],[411,5524],[672,10980],[672,10989],[672,10990],[672,11181],[672,13014],[672,1923],[672,194],[672,4566],[672,10993],[672,11355],[672,1834],[672,10983],[672,10965],[672,491],[672,293],[672,6875],[672,5491],[321697,17288],[321697,204],[321697,19274],[321697,8447],[321697,72873],[321697,77795],[321697,6585],[321697,1648751],[321697,1419742],[321697,235416],[321697,2034],[321697,11018],[321697,26192],[321697,11017],[161,1461],[161,287],[161,1271],[161,1892],[161,1204],[161,1893],[161,1894],[161,1896],[161,827],[161,1898],[161,1897],[161,1900],[161,1889],[161,1884],[161,1891],[161,1890],[161,1884],[163,1461],[163,1204],[163,287],[163,1892],[163,1922],[163,1271],[163,1893],[163,1896],[163,1897],[163,1894],[163,1925],[163,1898],[163,1884],[163,1890],[163,1889],[163,1891],[163,1884],[676,880],[676,2299],[676,3967],[676,10128],[676,10129],[676,1125],[676,7447],[676,5915],[676,10130],[676,9278],[676,10127],[676,9777],[676,947],[676,892],[676,10123],[676,898],[676,541],[676,2484],[676,9817],[676,865],[38050,1892],[38050,5081],[38050,21134],[38050,53650],[38050,50217],[38050,28641],[38050,83222],[38050,1124488],[38050,153],[38050,19755],[38050,2483],[177572,66580],[177572,515510],[177572,82093],[177572,51990],[177572,78324],[177572,87822],[177572,2505],[177572,21088],[38055,23659],[38055,287],[38055,56323],[38055,21007],[38055,212],[38055,7399],[38055,15009],[38055,936672],[38055,18864],[38055,18999],[38055,18864],[38055,947],[170,2037],[170,2038],[170,2039],[170,2058],[170,2040],[170,2050],[170,68307],[170,2258],[170,29237],[170,1570],[170,2071],[170,2034],[170,2070],[76203,5294],[76203,17288],[76203,1267329],[76203,71580],[76203,17142],[76203,34490],[76203,467633],[76203,59233],[76203,13242],[76203,287],[76203,39390],[76203,1981],[76203,999565],[76203,947],[501170,3061],[501170,933238],[501170,2118623],[501170,7248],[501170,42376],[501170,112742],[501170,1853396],[501170,79416],[617653,1892],[617653,1023139],[617653,1388593],[617653,880],[617653,17477],[617653,20982],[617653,1379277],[617653,84865],[617653,24627],[617653,6752],[617653,27631],[617653,944],[617653,11880],[617653,5553],[617653,120],[617653,578],[953,7399],[953,2632],[953,14409],[953,9575],[953,6730],[953,5726],[953,28637],[953,18864],[953,12097],[953,12098],[953,12080],[953,18863],[953,18863],[953,18864],[953,947],[953,15814],[953,56678],[953,1780681],[1213,1892],[1213,12052],[1213,9642],[1213,112],[1213,1233],[1213,1709],[1213,8986],[1213,15915],[1213,4492],[1213,1989],[1213,15916],[1213,5488],[374720,1687041],[374720,2524],[374720,40900],[374720,11181],[374720,2037],[374720,1290466],[374720,1052109],[374720,145143],[374720,579211],[374720,15327],[374720,947],[80321,7399],[80321,2632],[80321,14409],[80321,9575],[80321,3910],[80321,6730],[80321,28637],[80321,5726],[80321,83002],[80321,17419],[80321,519],[80321,3627],[80321,18863],[80321,947],[80321,18864],[80321,12080],[80321,44119],[80321,1780681],[197,2461],[197,2462],[197,1957],[197,2463],[197,2464],[197,2039],[197,2465],[197,2467],[197,2468],[197,2469],[197,2483],[197,2461],[197,1729],[197,2486],[197,2484],[2501,1892],[2501,679],[2501,2955],[2501,2296],[2501,1248],[2501,31164],[2501,32458],[2501,12041],[2501,27740],[2501,52419],[2501,11098],[2502,1892],[2502,679],[2502,1248],[2502,12041],[2502,1372],[2502,32458],[2502,11148],[2502,20982],[2502,27030],[2502,60118],[2502,166654],[2502,11705],[2502,11098],[2503,1892],[2503,12041],[2503,11064],[2503,349],[2503,14887],[2503,25616],[2503,3926],[2503,11148],[2503,27030],[2503,17199],[2503,3872],[2503,29406],[2503,11098],[58574,3223],[58574,9642],[58574,87722],[58574,15440],[58574,53714],[58574,1665],[58574,17521],[58574,11275],[58574,220448],[58574,11855],[58574,84865],[58574,659],[58574,956],[58574,947],[58574,36656],[58574,1301],[58574,56917],[10191,449],[10191,17276],[10191,24264],[10191,59174],[10191,21007],[10191,54691],[10191,51990],[10191,41091],[10191,130081],[10191,138619],[10191,1508424],[10191,15349],[10191,11098],[96721,74568],[96721,3872],[96721,59315],[96721,5644],[96721,17839],[96721,10779],[96721,58502],[96721,21345],[96721,56100],[96721,6159],[96721,947],[96721,1570],[96721,6189],[96721,20463],[96721,6190],[420818,5294],[420818,84292],[420818,119589],[420818,15152],[420818,51878],[420818,1981],[420818,14386],[420818,1828695],[420818,947],[9693,2296],[9693,64986],[9693,5294],[9693,1231],[9693,3895],[9693,11213],[9693,56365],[9693,6413],[9693,3064],[9693,81134],[9693,12210],[9693,58587],[9693,11218],[9693,11218],[9693,1253],[62177,9015],[62177,7056],[62177,9188],[62177,477],[62177,1923],[62177,9013],[62177,24264],[62177,1113604],[62177,137262],[62177,9152],[62177,7907],[62177,1052100],[62177,9152],[62177,126638],[62177,59803],[44264,1229],[44264,130640],[44264,1892],[44264,16851],[44264,12834],[44264,43364],[44264,54856],[44264,61260],[44264,93210],[44264,126713],[44264,1223],[44264,151],[44264,1224],[44264,10575],[44264,1224],[44264,1223],[44264,1225],[489,1892],[489,2157],[489,880],[489,1640],[489,6613],[489,1893],[489,6614],[489,6623],[489,6615],[489,6616],[489,950],[489,531],[102382,37625],[102382,54693],[102382,134],[102382,122889],[102382,10132],[102382,72855],[102382,13242],[102382,35],[102382,6368],[102382,20982],[102382,950],[102382,947],[497,31],[497,52],[497,5149],[497,61981],[497,2505],[497,2169],[497,6804],[497,6806],[497,6807],[497,12834],[497,12645],[497,153],[497,6800],[1272,2037],[1272,9827],[1272,16828],[1272,1620],[1272,7248],[1272,9195],[1272,31711],[1272,30082],[1272,2983],[1272,24618],[1272,1414389],[1272,2002163],[1272,2034],[1272,2071],[1272,26192],[1272,2070],[370172,8784],[370172,121529],[370172,17838],[370172,1360281],[370172,5469],[370172,17064],[370172,2038],[370172,139549],[370172,2954],[370172,141034],[370172,27319],[370172,93236],[370172,87257],[370172,1156888],[370172,11017],[370172,2071],[370172,947]]}